{
  "backupName": "BACKUP_20260225110000",
  "backupId": 37,
  "trigger": "AUTOMATIC",
  "timestamp": "2026-02-25_11-00-00",
  "database": {
    "included": true,
    "path": "D:\\Project\\it-helpdesk\\Data_Backup\\BACKUP_20260225110000.bak",
    "sizeMB": 12.99
  },
  "files": {
    "included": true,
    "path": "D:\\Project\\it-helpdesk\\Data_Backup\\2026-02-25_11-00-00\\files",
    "count": 13,
    "sizeMB": 7.37
  },
  "total": {
    "sizeMB": 20.36
  },
  "createdBy": null,
  "createdAt": "2026-02-25T11:00:00.749Z"
}